mail/__init__.py
mail/file_meta.py
mail/sender.py
mail_man_cbs_0.1-0.1.0.dist-info/METADATA
mail_man_cbs_0.1-0.1.0.dist-info/WHEEL
mail_man_cbs_0.1-0.1.0.dist-info/top_level.txt
mail_man_cbs_0.1-0.1.0.dist-info/RECORD
